cim_converter_eg/CIMModel.py
cim_converter_eg/__init__.py
cim_converter_eg/myfunctions.py
cim_converter_eg/rdf_converter.py
cim_converter_eg/CIM_EG/Element.py
cim_converter_eg/CIM_EG/__init__.py
cim_converter_eg/CIM_EG/AssetInfo/OverheadWireInfo.py
cim_converter_eg/CIM_EG/AssetInfo/TransformerEndInfo.py
cim_converter_eg/CIM_EG/AssetInfo/WireInfo.py
cim_converter_eg/CIM_EG/AssetInfo/__init__.py
cim_converter_eg/CIM_EG/AssetModels/NoLoadTest.py
cim_converter_eg/CIM_EG/AssetModels/ShortCircuitTest.py
cim_converter_eg/CIM_EG/AssetModels/TransformerTest.py
cim_converter_eg/CIM_EG/AssetModels/__init__.py
cim_converter_eg/CIM_EG/Assets/AssetInfo.py
cim_converter_eg/CIM_EG/Assets/__init__.py
cim_converter_eg/CIM_EG/AuxiliaryEquipment/AuxiliaryEquipment.py
cim_converter_eg/CIM_EG/AuxiliaryEquipment/CurrentTransformer.py
cim_converter_eg/CIM_EG/AuxiliaryEquipment/PotentialTransformer.py
cim_converter_eg/CIM_EG/AuxiliaryEquipment/Sensor.py
cim_converter_eg/CIM_EG/AuxiliaryEquipment/__init__.py
cim_converter_eg/CIM_EG/Common/CoordinateSystem.py
cim_converter_eg/CIM_EG/Common/Location.py
cim_converter_eg/CIM_EG/Common/PositionPoint.py
cim_converter_eg/CIM_EG/Common/__init__.py
cim_converter_eg/CIM_EG/Core/ACDCTerminal.py
cim_converter_eg/CIM_EG/Core/BaseVoltage.py
cim_converter_eg/CIM_EG/Core/Bay.py
cim_converter_eg/CIM_EG/Core/ConductingEquipment.py
cim_converter_eg/CIM_EG/Core/ConnectivityNode.py
cim_converter_eg/CIM_EG/Core/ConnectivityNodeContainer.py
cim_converter_eg/CIM_EG/Core/Equipment.py
cim_converter_eg/CIM_EG/Core/EquipmentContainer.py
cim_converter_eg/CIM_EG/Core/GeographicalRegion.py
cim_converter_eg/CIM_EG/Core/IdentifiedObject.py
cim_converter_eg/CIM_EG/Core/Name.py
cim_converter_eg/CIM_EG/Core/NameType.py
cim_converter_eg/CIM_EG/Core/NameTypeAuthority.py
cim_converter_eg/CIM_EG/Core/PowerSystemResource.py
cim_converter_eg/CIM_EG/Core/SubGeographicalRegion.py
cim_converter_eg/CIM_EG/Core/Substation.py
cim_converter_eg/CIM_EG/Core/Terminal.py
cim_converter_eg-0.1.1.dist-info/METADATA
cim_converter_eg-0.1.1.dist-info/WHEEL
cim_converter_eg-0.1.1.dist-info/top_level.txt
cim_converter_eg-0.1.1.dist-info/RECORD
