Metadata-Version: 2.1
Name: cim_converter_eg
Version: 0.1.1
Summary: CIM converter
Author: Matej Oblak
